makeflow/__init__.py
makeflow/cli.py
makeflow-0.0.1.dist-info/METADATA
makeflow-0.0.1.dist-info/WHEEL
makeflow-0.0.1.dist-info/entry_points.txt
makeflow-0.0.1.dist-info/top_level.txt
makeflow-0.0.1.dist-info/RECORD
