Metadata-Version: 2.2
Name: makeflow
Version: 0.0.1
Summary: Makefile based workflow for Python projects
Author-email: "Simon A. F. Lund" <os@safl.dk>
Maintainer-email: "Simon A. F. Lund" <os@safl.dk>
Project-URL: homepage, https://github.com/safl/makeflow
Project-URL: documentation, https://github.com/safl/makeflow/blob/main/README.rst
Project-URL: repository, https://github.com/safl/makeflow
Keywords: systems,development,testing
Classifier: Development Status :: 4 - Beta
Classifier: Environment :: Console
Classifier: Intended Audience :: System Administrators
Classifier: License :: OSI Approved :: BSD License
Classifier: Programming Language :: Python
Classifier: Topic :: Software Development
Classifier: Topic :: Text Processing
Classifier: Topic :: Utilities
Requires-Python: >=3.9
